rules_mcp_server-1.0.0.dist-info/licenses/LICENSE
src/__init__.py
src/config.py
src/file_watcher.py
src/models.py
src/rule_manager.py
src/tool_factory.py
rules_mcp_server-1.0.0.dist-info/METADATA
rules_mcp_server-1.0.0.dist-info/WHEEL
rules_mcp_server-1.0.0.dist-info/entry_points.txt
rules_mcp_server-1.0.0.dist-info/top_level.txt
rules_mcp_server-1.0.0.dist-info/RECORD
