Metadata-Version: 2.4
Name: rules-mcp-server
Version: 1.0.0
Summary: A Model Context Protocol server for development rules and best practices
Home-page: https://github.com/yourusername/rules-mcp-server
Author: Your Name
Author-email: Your Name <your.email@example.com>
License: MIT
Project-URL: Homepage, https://github.com/yourusername/rules-mcp-server
Project-URL: Bug Reports, https://github.com/yourusername/rules-mcp-server/issues
Project-URL: Source, https://github.com/yourusername/rules-mcp-server
Keywords: mcp,model-context-protocol,development-rules,best-practices,coding-standards
Classifier: Development Status :: 4 - Beta
Classifier: Intended Audience :: Developers
Classifier: Topic :: Software Development :: Libraries :: Python Modules
Classifier: License :: OSI Approved :: MIT License
Classifier: Programming Language :: Python :: 3
Classifier: Programming Language :: Python :: 3.8
Classifier: Programming Language :: Python :: 3.9
Classifier: Programming Language :: Python :: 3.10
Classifier: Programming Language :: Python :: 3.11
Classifier: Programming Language :: Python :: 3.12
Requires-Python: >=3.8
License-File: LICENSE
Requires-Dist: mcp>=1.0.0
Requires-Dist: fastmcp>=0.2.0
Requires-Dist: watchdog>=3.0.0
Requires-Dist: pydantic>=2.0.0
Dynamic: author
Dynamic: home-page
Dynamic: license-file
Dynamic: requires-python
